cturtle/__init__.py
cturtle/cturtle.py
cturtle-0.0.6.dist-info/COPYING.LESSER
cturtle-0.0.6.dist-info/LICENSE
cturtle-0.0.6.dist-info/METADATA
cturtle-0.0.6.dist-info/WHEEL
cturtle-0.0.6.dist-info/top_level.txt
cturtle-0.0.6.dist-info/RECORD
