Metadata-Version: 2.1
Name: cturtle
Version: 0.0.6
Summary: A ctypes interface to the TURTLE library
Home-page: https://github.com/niess/turtle-python
Author: Valentin Niess
Author-email: valentin.niess@gmail.com
License: UNKNOWN
Platform: UNKNOWN
Classifier: Programming Language :: Python
Classifier: Development Status :: 1 - Planning
Classifier: License :: OSI Approved :: GNU Lesser General Public License v3 (LGPLv3)
Classifier: Natural Language :: English
Classifier: Operating System :: OS Independent
Classifier: Programming Language :: Python :: 2.7
Classifier: Topic :: Scientific/Engineering :: Physics
